automate/__init__.py
automate/DataPreprocessor/Null_Value_Remover.py
automate/DataPreprocessor/__init__.py
automate/augmented_dickey_fuller_test/Augmented_Dickey_Fuller_Test.py
automate/augmented_dickey_fuller_test/Stationary_Converter.py
automate/augmented_dickey_fuller_test/__init__.py
automate/evaluation/__init__.py
automate/evaluation/metrics.py
automate/exponential_smoothening/Exponential_Smoothening.py
automate/exponential_smoothening/__init__.py
automate/machine_learning/Machine_Learning_Models.py
automate/machine_learning/__init__.py
automate/metrics/MetricsPrinter.py
automate/metrics/__init__.py
automate/null_value_remover/Null_Value_Remover.py
automate/null_value_remover/__init__.py
automate/statistical_models/Statistics_Models.py
neptune_automate-0.0.15.dist-info/LICENSE
neptune_automate-0.0.15.dist-info/METADATA
neptune_automate-0.0.15.dist-info/WHEEL
neptune_automate-0.0.15.dist-info/top_level.txt
neptune_automate-0.0.15.dist-info/RECORD
