Metadata-Version: 2.1
Name: neptune-automate
Version: 0.0.15
Summary: Machine Learning automation module
Author-email: Vrushal More <vrushal.more.work@gmail.com>
Project-URL: Homepage, https://github.com/vrushalMore/automate
Project-URL: Issues, https://github.com/vrushalMore/automate/issues
Classifier: Programming Language :: Python :: 3
Classifier: License :: OSI Approved :: MIT License
Classifier: Operating System :: OS Independent
Requires-Python: >=3.8
License-File: LICENSE
Requires-Dist: statsmodels
Requires-Dist: scikit-learn
Requires-Dist: xgboost
Requires-Dist: lightgbm
Requires-Dist: catboost
Requires-Dist: numpy
Requires-Dist: pandas
Requires-Dist: twine
Requires-Dist: setuptools
